arcaea_offline_ocr/__init__.py
arcaea_offline_ocr/crop.py
arcaea_offline_ocr/ocr.py
arcaea_offline_ocr/phash_db.py
arcaea_offline_ocr/types.py
arcaea_offline_ocr/utils.py
arcaea_offline_ocr/b30/__init__.py
arcaea_offline_ocr/b30/shared.py
arcaea_offline_ocr/b30/chieri/__init__.py
arcaea_offline_ocr/b30/chieri/v4/__init__.py
arcaea_offline_ocr/b30/chieri/v4/colors.py
arcaea_offline_ocr/b30/chieri/v4/ocr.py
arcaea_offline_ocr/b30/chieri/v4/rois.py
arcaea_offline_ocr/device/__init__.py
arcaea_offline_ocr/device/common.py
arcaea_offline_ocr/device/ocr.py
arcaea_offline_ocr/device/rois/__init__.py
arcaea_offline_ocr/device/rois/definition/__init__.py
arcaea_offline_ocr/device/rois/definition/auto.py
arcaea_offline_ocr/device/rois/definition/common.py
arcaea_offline_ocr/device/rois/definition/custom.py
arcaea_offline_ocr/device/rois/extractor/__init__.py
arcaea_offline_ocr/device/rois/extractor/common.py
arcaea_offline_ocr/device/rois/masker/__init__.py
arcaea_offline_ocr/device/rois/masker/auto.py
arcaea_offline_ocr/device/rois/masker/common.py
arcaea_offline_ocr-0.0.99.dist-info/LICENSE
arcaea_offline_ocr-0.0.99.dist-info/METADATA
arcaea_offline_ocr-0.0.99.dist-info/WHEEL
arcaea_offline_ocr-0.0.99.dist-info/top_level.txt
arcaea_offline_ocr-0.0.99.dist-info/RECORD
