Metadata-Version: 2.1
Name: arcaea-offline-ocr
Version: 0.0.99
Summary: Extract your Arcaea play result from screenshot.
Author-email: 283375 <log_283375@163.com>
Project-URL: Homepage, https://github.com/ArcaeaOffline/core-ocr
Project-URL: Bug Tracker, https://github.com/ArcaeaOffline/core-ocr/issues
Classifier: Development Status :: 3 - Alpha
Classifier: Programming Language :: Python :: 3
Requires-Python: >=3.8
License-File: LICENSE
Requires-Dist: attrs ==23.1.0
Requires-Dist: numpy ==1.26.1
Requires-Dist: opencv-python ==4.8.1.78
